langchain_autotools/__init__.py
langchain_autotools/langchain_autotools.py
langchain_autotools-0.1.0.dist-info/LICENSE
langchain_autotools-0.1.0.dist-info/METADATA
langchain_autotools-0.1.0.dist-info/WHEEL
langchain_autotools-0.1.0.dist-info/RECORD
