Metadata-Version: 2.1
Name: langchain-autotools
Version: 0.1.0
Summary: Automatic Langchain Tool and Toolkit creation from any Python SDK!
License: MIT
Author: James Barney
Author-email: james@southendsolutions.com
Requires-Python: >=3.10,<4.0
Classifier: License :: OSI Approved :: MIT License
Classifier: Programming Language :: Python :: 3
Classifier: Programming Language :: Python :: 3.10
Classifier: Programming Language :: Python :: 3.11
Classifier: Programming Language :: Python :: 3.12
Classifier: Programming Language :: Python :: 3.13
Requires-Dist: langchain (>=0.3,<0.4)
